vodafone_station/__init__.py
vodafone_station/__main__.py
vodafone_station/abstract_vodafone_station.py
vodafone_station/cli.py
vodafone_station/config.py
vodafone_station/default_config.json
vodafone_station/main.py
vodafone_station/util.py
vodafone_station/vodafone_station_abstract.py
vodafone_station/vodafone_station_class.py
vodafone_station-0.1.5.dist-info/LICENSE
vodafone_station-0.1.5.dist-info/METADATA
vodafone_station-0.1.5.dist-info/WHEEL
vodafone_station-0.1.5.dist-info/entry_points.txt
vodafone_station-0.1.5.dist-info/top_level.txt
vodafone_station-0.1.5.dist-info/RECORD
